odoo/addons/purchase_total_ordered_qty/README.rst
odoo/addons/purchase_total_ordered_qty/__init__.py
odoo/addons/purchase_total_ordered_qty/__manifest__.py
odoo/addons/purchase_total_ordered_qty/i18n/es.po
odoo/addons/purchase_total_ordered_qty/i18n/fr.po
odoo/addons/purchase_total_ordered_qty/i18n/purchase_total_ordered_qty.pot
odoo/addons/purchase_total_ordered_qty/models/__init__.py
odoo/addons/purchase_total_ordered_qty/models/purchase_order.py
odoo/addons/purchase_total_ordered_qty/readme/CONTRIBUTORS.rst
odoo/addons/purchase_total_ordered_qty/readme/DESCRIPTION.rst
odoo/addons/purchase_total_ordered_qty/static/description/icon.png
odoo/addons/purchase_total_ordered_qty/static/description/index.html
odoo/addons/purchase_total_ordered_qty/tests/__init__.py
odoo/addons/purchase_total_ordered_qty/tests/test_purchase_total_ordered_qty.py
odoo/addons/purchase_total_ordered_qty/views/purchase_order.xml
odoo_addon_purchase_total_ordered_qty-15.0.1.0.0.6.dist-info/METADATA
odoo_addon_purchase_total_ordered_qty-15.0.1.0.0.6.dist-info/WHEEL
odoo_addon_purchase_total_ordered_qty-15.0.1.0.0.6.dist-info/top_level.txt
odoo_addon_purchase_total_ordered_qty-15.0.1.0.0.6.dist-info/RECORD
